llm_tools_todo.py
llm_tools_todo-0.3.dist-info/licenses/LICENSE
llm_tools_todo-0.3.dist-info/METADATA
llm_tools_todo-0.3.dist-info/WHEEL
llm_tools_todo-0.3.dist-info/entry_points.txt
llm_tools_todo-0.3.dist-info/top_level.txt
llm_tools_todo-0.3.dist-info/RECORD
