Metadata-Version: 2.4
Name: llm-tools-todo
Version: 0.3
Summary: LLM tools for todo management
Author-email: Danny O'Brien <danny@spesh.com>
License-Expression: Apache-2.0
Project-URL: Homepage, https://github.com/dannyob/llm-tools-todo
Project-URL: Changelog, https://github.com/dannyob/llm-tools-todo/releases
Project-URL: Issues, https://github.com/dannyob/llm-tools-todo/issues
Project-URL: CI, https://github.com/dannyob/llm-tools-todo/actions
Requires-Python: >=3.9
License-File: LICENSE
Requires-Dist: llm>=0.26
Requires-Dist: pydantic
Provides-Extra: test
Requires-Dist: pytest; extra == "test"
Requires-Dist: llm-echo>=0.3a1; extra == "test"
Dynamic: license-file
